{
  "kind": "osdu:wks:Manifest:1.0.0",
  "ReferenceData": [
    {
      "id": "{{NAMESPACE}}:reference-data--GeoMagneticModel:BGGM95",
      "kind": "osdu:wks:reference-data--GeoMagneticModel:1.0.0",
      "acl": {
        "owners": [
          "{{DATA_OWNERS_GROUP}}"
        ],
        "viewers": [
          "{{DATA_VIEWERS_GROUP}}"
        ]
      },
      "legal": {
        "legaltags": [
          "{{LEGAL_TAG}}"
        ],
        "otherRelevantDataCountries": [
          "{{ISO_3166_ALPHA_2_CODE}}"
        ]
      },
      "data": {
        "Name": "BGGM 1995",
        "ID": "BGGM95",
        "Description": "British Geological Survey Global Geomagnetic Model 1995",
        "Code": "BGGM95",
        "AttributionAuthority": "British Geological Survey (BGS)",
        "AttributionPublication": "https://geomag.bgs.ac.uk/data_service/directionaldrilling/bggm.html",
        "AttributionRevision": "1995",
        "Source": "Workbook ReferenceValues/Published/GeoMagneticModel.1.xlsx; commit SHA e3ae7f79.",
        "CommitDate": "2024-07-04T12:33:51+00:00"
      }
    },
    {
      "id": "{{NAMESPACE}}:reference-data--GeoMagneticModel:BGGM96",
      "kind": "osdu:wks:reference-data--GeoMagneticModel:1.0.0",
      "acl": {
        "owners": [
          "{{DATA_OWNERS_GROUP}}"
        ],
        "viewers": [
          "{{DATA_VIEWERS_GROUP}}"
        ]
      },
      "legal": {
        "legaltags": [
          "{{LEGAL_TAG}}"
        ],
        "otherRelevantDataCountries": [
          "{{ISO_3166_ALPHA_2_CODE}}"
        ]
      },
      "data": {
        "Name": "BGGM 1996",
        "ID": "BGGM96",
        "Description": "British Geological Survey Global Geomagnetic Model 1996",
        "Code": "BGGM96",
        "AttributionAuthority": "British Geological Survey (BGS)",
        "AttributionPublication": "https://geomag.bgs.ac.uk/data_service/directionaldrilling/bggm.html",
        "AttributionRevision": "1996",
        "Source": "Workbook ReferenceValues/Published/GeoMagneticModel.1.xlsx; commit SHA e3ae7f79.",
        "CommitDate": "2024-07-04T12:33:51+00:00"
      }
    },
    {
      "id": "{{NAMESPACE}}:reference-data--GeoMagneticModel:BGGM97",
      "kind": "osdu:wks:reference-data--GeoMagneticModel:1.0.0",
      "acl": {
        "owners": [
          "{{DATA_OWNERS_GROUP}}"
        ],
        "viewers": [
          "{{DATA_VIEWERS_GROUP}}"
        ]
      },
      "legal": {
        "legaltags": [
          "{{LEGAL_TAG}}"
        ],
        "otherRelevantDataCountries": [
          "{{ISO_3166_ALPHA_2_CODE}}"
        ]
      },
      "data": {
        "Name": "BGGM 1997",
        "ID": "BGGM97",
        "Description": "British Geological Survey Global Geomagnetic Model 1997",
        "Code": "BGGM97",
        "AttributionAuthority": "British Geological Survey (BGS)",
        "AttributionPublication": "https://geomag.bgs.ac.uk/data_service/directionaldrilling/bggm.html",
        "AttributionRevision": "1997",
        "Source": "Workbook ReferenceValues/Published/GeoMagneticModel.1.xlsx; commit SHA e3ae7f79.",
        "CommitDate": "2024-07-04T12:33:51+00:00"
      }
    },
    {
      "id": "{{NAMESPACE}}:reference-data--GeoMagneticModel:BGGM98",
      "kind": "osdu:wks:reference-data--GeoMagneticModel:1.0.0",
      "acl": {
        "owners": [
          "{{DATA_OWNERS_GROUP}}"
        ],
        "viewers": [
          "{{DATA_VIEWERS_GROUP}}"
        ]
      },
      "legal": {
        "legaltags": [
          "{{LEGAL_TAG}}"
        ],
        "otherRelevantDataCountries": [
          "{{ISO_3166_ALPHA_2_CODE}}"
        ]
      },
      "data": {
        "Name": "BGGM 1998",
        "ID": "BGGM98",
        "Description": "British Geological Survey Global Geomagnetic Model 1998",
        "Code": "BGGM98",
        "AttributionAuthority": "British Geological Survey (BGS)",
        "AttributionPublication": "https://geomag.bgs.ac.uk/data_service/directionaldrilling/bggm.html",
        "AttributionRevision": "1998",
        "Source": "Workbook ReferenceValues/Published/GeoMagneticModel.1.xlsx; commit SHA e3ae7f79.",
        "CommitDate": "2024-07-04T12:33:51+00:00"
      }
    },
    {
      "id": "{{NAMESPACE}}:reference-data--GeoMagneticModel:BGGM99",
      "kind": "osdu:wks:reference-data--GeoMagneticModel:1.0.0",
      "acl": {
        "owners": [
          "{{DATA_OWNERS_GROUP}}"
        ],
        "viewers": [
          "{{DATA_VIEWERS_GROUP}}"
        ]
      },
      "legal": {
        "legaltags": [
          "{{LEGAL_TAG}}"
        ],
        "otherRelevantDataCountries": [
          "{{ISO_3166_ALPHA_2_CODE}}"
        ]
      },
      "data": {
        "Name": "BGGM 1999",
        "ID": "BGGM99",
        "Description": "British Geological Survey Global Geomagnetic Model 1999",
        "Code": "BGGM99",
        "AttributionAuthority": "British Geological Survey (BGS)",
        "AttributionPublication": "https://geomag.bgs.ac.uk/data_service/directionaldrilling/bggm.html",
        "AttributionRevision": "1999",
        "Source": "Workbook ReferenceValues/Published/GeoMagneticModel.1.xlsx; commit SHA e3ae7f79.",
        "CommitDate": "2024-07-04T12:33:51+00:00"
      }
    },
    {
      "id": "{{NAMESPACE}}:reference-data--GeoMagneticModel:BGGM2000",
      "kind": "osdu:wks:reference-data--GeoMagneticModel:1.0.0",
      "acl": {
        "owners": [
          "{{DATA_OWNERS_GROUP}}"
        ],
        "viewers": [
          "{{DATA_VIEWERS_GROUP}}"
        ]
      },
      "legal": {
        "legaltags": [
          "{{LEGAL_TAG}}"
        ],
        "otherRelevantDataCountries": [
          "{{ISO_3166_ALPHA_2_CODE}}"
        ]
      },
      "data": {
        "Name": "BGGM 2000",
        "ID": "BGGM2000",
        "Description": "British Geological Survey Global Geomagnetic Model 2000",
        "Code": "BGGM2000",
        "AttributionAuthority": "British Geological Survey (BGS)",
        "AttributionPublication": "https://geomag.bgs.ac.uk/data_service/directionaldrilling/bggm.html",
        "AttributionRevision": "2000",
        "Source": "Workbook ReferenceValues/Published/GeoMagneticModel.1.xlsx; commit SHA e3ae7f79.",
        "CommitDate": "2024-07-04T12:33:51+00:00"
      }
    },
    {
      "id": "{{NAMESPACE}}:reference-data--GeoMagneticModel:BGGM2001",
      "kind": "osdu:wks:reference-data--GeoMagneticModel:1.0.0",
      "acl": {
        "owners": [
          "{{DATA_OWNERS_GROUP}}"
        ],
        "viewers": [
          "{{DATA_VIEWERS_GROUP}}"
        ]
      },
      "legal": {
        "legaltags": [
          "{{LEGAL_TAG}}"
        ],
        "otherRelevantDataCountries": [
          "{{ISO_3166_ALPHA_2_CODE}}"
        ]
      },
      "data": {
        "Name": "BGGM 2001",
        "ID": "BGGM2001",
        "Description": "British Geological Survey Global Geomagnetic Model 2001",
        "Code": "BGGM2001",
        "AttributionAuthority": "British Geological Survey (BGS)",
        "AttributionPublication": "https://geomag.bgs.ac.uk/data_service/directionaldrilling/bggm.html",
        "AttributionRevision": "2001",
        "Source": "Workbook ReferenceValues/Published/GeoMagneticModel.1.xlsx; commit SHA e3ae7f79.",
        "CommitDate": "2024-07-04T12:33:51+00:00"
      }
    },
    {
      "id": "{{NAMESPACE}}:reference-data--GeoMagneticModel:BGGM2002",
      "kind": "osdu:wks:reference-data--GeoMagneticModel:1.0.0",
      "acl": {
        "owners": [
          "{{DATA_OWNERS_GROUP}}"
        ],
        "viewers": [
          "{{DATA_VIEWERS_GROUP}}"
        ]
      },
      "legal": {
        "legaltags": [
          "{{LEGAL_TAG}}"
        ],
        "otherRelevantDataCountries": [
          "{{ISO_3166_ALPHA_2_CODE}}"
        ]
      },
      "data": {
        "Name": "BGGM 2002",
        "ID": "BGGM2002",
        "Description": "British Geological Survey Global Geomagnetic Model 2002",
        "Code": "BGGM2002",
        "AttributionAuthority": "British Geological Survey (BGS)",
        "AttributionPublication": "https://geomag.bgs.ac.uk/data_service/directionaldrilling/bggm.html",
        "AttributionRevision": "2002",
        "Source": "Workbook ReferenceValues/Published/GeoMagneticModel.1.xlsx; commit SHA e3ae7f79.",
        "CommitDate": "2024-07-04T12:33:51+00:00"
      }
    },
    {
      "id": "{{NAMESPACE}}:reference-data--GeoMagneticModel:BGGM2003",
      "kind": "osdu:wks:reference-data--GeoMagneticModel:1.0.0",
      "acl": {
        "owners": [
          "{{DATA_OWNERS_GROUP}}"
        ],
        "viewers": [
          "{{DATA_VIEWERS_GROUP}}"
        ]
      },
      "legal": {
        "legaltags": [
          "{{LEGAL_TAG}}"
        ],
        "otherRelevantDataCountries": [
          "{{ISO_3166_ALPHA_2_CODE}}"
        ]
      },
      "data": {
        "Name": "BGGM 2003",
        "ID": "BGGM2003",
        "Description": "British Geological Survey Global Geomagnetic Model 2003",
        "Code": "BGGM2003",
        "AttributionAuthority": "British Geological Survey (BGS)",
        "AttributionPublication": "https://geomag.bgs.ac.uk/data_service/directionaldrilling/bggm.html",
        "AttributionRevision": "2003",
        "Source": "Workbook ReferenceValues/Published/GeoMagneticModel.1.xlsx; commit SHA e3ae7f79.",
        "CommitDate": "2024-07-04T12:33:51+00:00"
      }
    },
    {
      "id": "{{NAMESPACE}}:reference-data--GeoMagneticModel:BGGM2004",
      "kind": "osdu:wks:reference-data--GeoMagneticModel:1.0.0",
      "acl": {
        "owners": [
          "{{DATA_OWNERS_GROUP}}"
        ],
        "viewers": [
          "{{DATA_VIEWERS_GROUP}}"
        ]
      },
      "legal": {
        "legaltags": [
          "{{LEGAL_TAG}}"
        ],
        "otherRelevantDataCountries": [
          "{{ISO_3166_ALPHA_2_CODE}}"
        ]
      },
      "data": {
        "Name": "BGGM 2004",
        "ID": "BGGM2004",
        "Description": "British Geological Survey Global Geomagnetic Model 2004",
        "Code": "BGGM2004",
        "AttributionAuthority": "British Geological Survey (BGS)",
        "AttributionPublication": "https://geomag.bgs.ac.uk/data_service/directionaldrilling/bggm.html",
        "AttributionRevision": "2004",
        "Source": "Workbook ReferenceValues/Published/GeoMagneticModel.1.xlsx; commit SHA e3ae7f79.",
        "CommitDate": "2024-07-04T12:33:51+00:00"
      }
    },
    {
      "id": "{{NAMESPACE}}:reference-data--GeoMagneticModel:BGGM2005",
      "kind": "osdu:wks:reference-data--GeoMagneticModel:1.0.0",
      "acl": {
        "owners": [
          "{{DATA_OWNERS_GROUP}}"
        ],
        "viewers": [
          "{{DATA_VIEWERS_GROUP}}"
        ]
      },
      "legal": {
        "legaltags": [
          "{{LEGAL_TAG}}"
        ],
        "otherRelevantDataCountries": [
          "{{ISO_3166_ALPHA_2_CODE}}"
        ]
      },
      "data": {
        "Name": "BGGM 2005",
        "ID": "BGGM2005",
        "Description": "British Geological Survey Global Geomagnetic Model 2005",
        "Code": "BGGM2005",
        "AttributionAuthority": "British Geological Survey (BGS)",
        "AttributionPublication": "https://geomag.bgs.ac.uk/data_service/directionaldrilling/bggm.html",
        "AttributionRevision": "2005",
        "Source": "Workbook ReferenceValues/Published/GeoMagneticModel.1.xlsx; commit SHA e3ae7f79.",
        "CommitDate": "2024-07-04T12:33:51+00:00"
      }
    },
    {
      "id": "{{NAMESPACE}}:reference-data--GeoMagneticModel:BGGM2006",
      "kind": "osdu:wks:reference-data--GeoMagneticModel:1.0.0",
      "acl": {
        "owners": [
          "{{DATA_OWNERS_GROUP}}"
        ],
        "viewers": [
          "{{DATA_VIEWERS_GROUP}}"
        ]
      },
      "legal": {
        "legaltags": [
          "{{LEGAL_TAG}}"
        ],
        "otherRelevantDataCountries": [
          "{{ISO_3166_ALPHA_2_CODE}}"
        ]
      },
      "data": {
        "Name": "BGGM 2006",
        "ID": "BGGM2006",
        "Description": "British Geological Survey Global Geomagnetic Model 2006",
        "Code": "BGGM2006",
        "AttributionAuthority": "British Geological Survey (BGS)",
        "AttributionPublication": "https://geomag.bgs.ac.uk/data_service/directionaldrilling/bggm.html",
        "AttributionRevision": "2006",
        "Source": "Workbook ReferenceValues/Published/GeoMagneticModel.1.xlsx; commit SHA e3ae7f79.",
        "CommitDate": "2024-07-04T12:33:51+00:00"
      }
    },
    {
      "id": "{{NAMESPACE}}:reference-data--GeoMagneticModel:BGGM2007",
      "kind": "osdu:wks:reference-data--GeoMagneticModel:1.0.0",
      "acl": {
        "owners": [
          "{{DATA_OWNERS_GROUP}}"
        ],
        "viewers": [
          "{{DATA_VIEWERS_GROUP}}"
        ]
      },
      "legal": {
        "legaltags": [
          "{{LEGAL_TAG}}"
        ],
        "otherRelevantDataCountries": [
          "{{ISO_3166_ALPHA_2_CODE}}"
        ]
      },
      "data": {
        "Name": "BGGM 2007",
        "ID": "BGGM2007",
        "Description": "British Geological Survey Global Geomagnetic Model 2007",
        "Code": "BGGM2007",
        "AttributionAuthority": "British Geological Survey (BGS)",
        "AttributionPublication": "https://geomag.bgs.ac.uk/data_service/directionaldrilling/bggm.html",
        "AttributionRevision": "2007",
        "Source": "Workbook ReferenceValues/Published/GeoMagneticModel.1.xlsx; commit SHA e3ae7f79.",
        "CommitDate": "2024-07-04T12:33:51+00:00"
      }
    },
    {
      "id": "{{NAMESPACE}}:reference-data--GeoMagneticModel:BGGM2008",
      "kind": "osdu:wks:reference-data--GeoMagneticModel:1.0.0",
      "acl": {
        "owners": [
          "{{DATA_OWNERS_GROUP}}"
        ],
        "viewers": [
          "{{DATA_VIEWERS_GROUP}}"
        ]
      },
      "legal": {
        "legaltags": [
          "{{LEGAL_TAG}}"
        ],
        "otherRelevantDataCountries": [
          "{{ISO_3166_ALPHA_2_CODE}}"
        ]
      },
      "data": {
        "Name": "BGGM 2008",
        "ID": "BGGM2008",
        "Description": "British Geological Survey Global Geomagnetic Model 2008",
        "Code": "BGGM2008",
        "AttributionAuthority": "British Geological Survey (BGS)",
        "AttributionPublication": "https://geomag.bgs.ac.uk/data_service/directionaldrilling/bggm.html",
        "AttributionRevision": "2008",
        "Source": "Workbook ReferenceValues/Published/GeoMagneticModel.1.xlsx; commit SHA e3ae7f79.",
        "CommitDate": "2024-07-04T12:33:51+00:00"
      }
    },
    {
      "id": "{{NAMESPACE}}:reference-data--GeoMagneticModel:BGGM2009",
      "kind": "osdu:wks:reference-data--GeoMagneticModel:1.0.0",
      "acl": {
        "owners": [
          "{{DATA_OWNERS_GROUP}}"
        ],
        "viewers": [
          "{{DATA_VIEWERS_GROUP}}"
        ]
      },
      "legal": {
        "legaltags": [
          "{{LEGAL_TAG}}"
        ],
        "otherRelevantDataCountries": [
          "{{ISO_3166_ALPHA_2_CODE}}"
        ]
      },
      "data": {
        "Name": "BGGM 2009",
        "ID": "BGGM2009",
        "Description": "British Geological Survey Global Geomagnetic Model 2009",
        "Code": "BGGM2009",
        "AttributionAuthority": "British Geological Survey (BGS)",
        "AttributionPublication": "https://geomag.bgs.ac.uk/data_service/directionaldrilling/bggm.html",
        "AttributionRevision": "2009",
        "Source": "Workbook ReferenceValues/Published/GeoMagneticModel.1.xlsx; commit SHA e3ae7f79.",
        "CommitDate": "2024-07-04T12:33:51+00:00"
      }
    },
    {
      "id": "{{NAMESPACE}}:reference-data--GeoMagneticModel:BGGM2010",
      "kind": "osdu:wks:reference-data--GeoMagneticModel:1.0.0",
      "acl": {
        "owners": [
          "{{DATA_OWNERS_GROUP}}"
        ],
        "viewers": [
          "{{DATA_VIEWERS_GROUP}}"
        ]
      },
      "legal": {
        "legaltags": [
          "{{LEGAL_TAG}}"
        ],
        "otherRelevantDataCountries": [
          "{{ISO_3166_ALPHA_2_CODE}}"
        ]
      },
      "data": {
        "Name": "BGGM 2010",
        "ID": "BGGM2010",
        "Description": "British Geological Survey Global Geomagnetic Model 2010",
        "Code": "BGGM2010",
        "AttributionAuthority": "British Geological Survey (BGS)",
        "AttributionPublication": "https://geomag.bgs.ac.uk/data_service/directionaldrilling/bggm.html",
        "AttributionRevision": "2010",
        "Source": "Workbook ReferenceValues/Published/GeoMagneticModel.1.xlsx; commit SHA e3ae7f79.",
        "CommitDate": "2024-07-04T12:33:51+00:00"
      }
    },
    {
      "id": "{{NAMESPACE}}:reference-data--GeoMagneticModel:BGGM2011",
      "kind": "osdu:wks:reference-data--GeoMagneticModel:1.0.0",
      "acl": {
        "owners": [
          "{{DATA_OWNERS_GROUP}}"
        ],
        "viewers": [
          "{{DATA_VIEWERS_GROUP}}"
        ]
      },
      "legal": {
        "legaltags": [
          "{{LEGAL_TAG}}"
        ],
        "otherRelevantDataCountries": [
          "{{ISO_3166_ALPHA_2_CODE}}"
        ]
      },
      "data": {
        "Name": "BGGM 2011",
        "ID": "BGGM2011",
        "Description": "British Geological Survey Global Geomagnetic Model 2011",
        "Code": "BGGM2011",
        "AttributionAuthority": "British Geological Survey (BGS)",
        "AttributionPublication": "https://geomag.bgs.ac.uk/data_service/directionaldrilling/bggm.html",
        "AttributionRevision": "2011",
        "Source": "Workbook ReferenceValues/Published/GeoMagneticModel.1.xlsx; commit SHA e3ae7f79.",
        "CommitDate": "2024-07-04T12:33:51+00:00"
      }
    },
    {
      "id": "{{NAMESPACE}}:reference-data--GeoMagneticModel:BGGM2012",
      "kind": "osdu:wks:reference-data--GeoMagneticModel:1.0.0",
      "acl": {
        "owners": [
          "{{DATA_OWNERS_GROUP}}"
        ],
        "viewers": [
          "{{DATA_VIEWERS_GROUP}}"
        ]
      },
      "legal": {
        "legaltags": [
          "{{LEGAL_TAG}}"
        ],
        "otherRelevantDataCountries": [
          "{{ISO_3166_ALPHA_2_CODE}}"
        ]
      },
      "data": {
        "Name": "BGGM 2012",
        "ID": "BGGM2012",
        "Description": "British Geological Survey Global Geomagnetic Model 2012",
        "Code": "BGGM2012",
        "AttributionAuthority": "British Geological Survey (BGS)",
        "AttributionPublication": "https://geomag.bgs.ac.uk/data_service/directionaldrilling/bggm.html",
        "AttributionRevision": "2012",
        "Source": "Workbook ReferenceValues/Published/GeoMagneticModel.1.xlsx; commit SHA e3ae7f79.",
        "CommitDate": "2024-07-04T12:33:51+00:00"
      }
    },
    {
      "id": "{{NAMESPACE}}:reference-data--GeoMagneticModel:BGGM2013",
      "kind": "osdu:wks:reference-data--GeoMagneticModel:1.0.0",
      "acl": {
        "owners": [
          "{{DATA_OWNERS_GROUP}}"
        ],
        "viewers": [
          "{{DATA_VIEWERS_GROUP}}"
        ]
      },
      "legal": {
        "legaltags": [
          "{{LEGAL_TAG}}"
        ],
        "otherRelevantDataCountries": [
          "{{ISO_3166_ALPHA_2_CODE}}"
        ]
      },
      "data": {
        "Name": "BGGM 2013",
        "ID": "BGGM2013",
        "Description": "British Geological Survey Global Geomagnetic Model 2013",
        "Code": "BGGM2013",
        "AttributionAuthority": "British Geological Survey (BGS)",
        "AttributionPublication": "https://geomag.bgs.ac.uk/data_service/directionaldrilling/bggm.html",
        "AttributionRevision": "2013",
        "Source": "Workbook ReferenceValues/Published/GeoMagneticModel.1.xlsx; commit SHA e3ae7f79.",
        "CommitDate": "2024-07-04T12:33:51+00:00"
      }
    },
    {
      "id": "{{NAMESPACE}}:reference-data--GeoMagneticModel:BGGM2014",
      "kind": "osdu:wks:reference-data--GeoMagneticModel:1.0.0",
      "acl": {
        "owners": [
          "{{DATA_OWNERS_GROUP}}"
        ],
        "viewers": [
          "{{DATA_VIEWERS_GROUP}}"
        ]
      },
      "legal": {
        "legaltags": [
          "{{LEGAL_TAG}}"
        ],
        "otherRelevantDataCountries": [
          "{{ISO_3166_ALPHA_2_CODE}}"
        ]
      },
      "data": {
        "Name": "BGGM 2014",
        "ID": "BGGM2014",
        "Description": "British Geological Survey Global Geomagnetic Model 2014",
        "Code": "BGGM2014",
        "AttributionAuthority": "British Geological Survey (BGS)",
        "AttributionPublication": "https://geomag.bgs.ac.uk/data_service/directionaldrilling/bggm.html",
        "AttributionRevision": "2014",
        "Source": "Workbook ReferenceValues/Published/GeoMagneticModel.1.xlsx; commit SHA e3ae7f79.",
        "CommitDate": "2024-07-04T12:33:51+00:00"
      }
    },
    {
      "id": "{{NAMESPACE}}:reference-data--GeoMagneticModel:BGGM2015",
      "kind": "osdu:wks:reference-data--GeoMagneticModel:1.0.0",
      "acl": {
        "owners": [
          "{{DATA_OWNERS_GROUP}}"
        ],
        "viewers": [
          "{{DATA_VIEWERS_GROUP}}"
        ]
      },
      "legal": {
        "legaltags": [
          "{{LEGAL_TAG}}"
        ],
        "otherRelevantDataCountries": [
          "{{ISO_3166_ALPHA_2_CODE}}"
        ]
      },
      "data": {
        "Name": "BGGM 2015",
        "ID": "BGGM2015",
        "Description": "British Geological Survey Global Geomagnetic Model 2015",
        "Code": "BGGM2015",
        "AttributionAuthority": "British Geological Survey (BGS)",
        "AttributionPublication": "https://geomag.bgs.ac.uk/data_service/directionaldrilling/bggm.html",
        "AttributionRevision": "2015",
        "Source": "Workbook ReferenceValues/Published/GeoMagneticModel.1.xlsx; commit SHA e3ae7f79.",
        "CommitDate": "2024-07-04T12:33:51+00:00"
      }
    },
    {
      "id": "{{NAMESPACE}}:reference-data--GeoMagneticModel:BGGM2016",
      "kind": "osdu:wks:reference-data--GeoMagneticModel:1.0.0",
      "acl": {
        "owners": [
          "{{DATA_OWNERS_GROUP}}"
        ],
        "viewers": [
          "{{DATA_VIEWERS_GROUP}}"
        ]
      },
      "legal": {
        "legaltags": [
          "{{LEGAL_TAG}}"
        ],
        "otherRelevantDataCountries": [
          "{{ISO_3166_ALPHA_2_CODE}}"
        ]
      },
      "data": {
        "Name": "BGGM 2016",
        "ID": "BGGM2016",
        "Description": "British Geological Survey Global Geomagnetic Model 2016",
        "Code": "BGGM2016",
        "AttributionAuthority": "British Geological Survey (BGS)",
        "AttributionPublication": "https://geomag.bgs.ac.uk/data_service/directionaldrilling/bggm.html",
        "AttributionRevision": "2016",
        "Source": "Workbook ReferenceValues/Published/GeoMagneticModel.1.xlsx; commit SHA e3ae7f79.",
        "CommitDate": "2024-07-04T12:33:51+00:00"
      }
    },
    {
      "id": "{{NAMESPACE}}:reference-data--GeoMagneticModel:BGGM2017",
      "kind": "osdu:wks:reference-data--GeoMagneticModel:1.0.0",
      "acl": {
        "owners": [
          "{{DATA_OWNERS_GROUP}}"
        ],
        "viewers": [
          "{{DATA_VIEWERS_GROUP}}"
        ]
      },
      "legal": {
        "legaltags": [
          "{{LEGAL_TAG}}"
        ],
        "otherRelevantDataCountries": [
          "{{ISO_3166_ALPHA_2_CODE}}"
        ]
      },
      "data": {
        "Name": "BGGM 2017",
        "ID": "BGGM2017",
        "Description": "British Geological Survey Global Geomagnetic Model 2017",
        "Code": "BGGM2017",
        "AttributionAuthority": "British Geological Survey (BGS)",
        "AttributionPublication": "https://geomag.bgs.ac.uk/data_service/directionaldrilling/bggm.html",
        "AttributionRevision": "2017",
        "Source": "Workbook ReferenceValues/Published/GeoMagneticModel.1.xlsx; commit SHA e3ae7f79.",
        "CommitDate": "2024-07-04T12:33:51+00:00"
      }
    },
    {
      "id": "{{NAMESPACE}}:reference-data--GeoMagneticModel:BGGM2018",
      "kind": "osdu:wks:reference-data--GeoMagneticModel:1.0.0",
      "acl": {
        "owners": [
          "{{DATA_OWNERS_GROUP}}"
        ],
        "viewers": [
          "{{DATA_VIEWERS_GROUP}}"
        ]
      },
      "legal": {
        "legaltags": [
          "{{LEGAL_TAG}}"
        ],
        "otherRelevantDataCountries": [
          "{{ISO_3166_ALPHA_2_CODE}}"
        ]
      },
      "data": {
        "Name": "BGGM 2018",
        "ID": "BGGM2018",
        "Description": "British Geological Survey Global Geomagnetic Model 2018",
        "Code": "BGGM2018",
        "AttributionAuthority": "British Geological Survey (BGS)",
        "AttributionPublication": "https://geomag.bgs.ac.uk/data_service/directionaldrilling/bggm.html",
        "AttributionRevision": "2018",
        "Source": "Workbook ReferenceValues/Published/GeoMagneticModel.1.xlsx; commit SHA e3ae7f79.",
        "CommitDate": "2024-07-04T12:33:51+00:00"
      }
    },
    {
      "id": "{{NAMESPACE}}:reference-data--GeoMagneticModel:BGGM2019",
      "kind": "osdu:wks:reference-data--GeoMagneticModel:1.0.0",
      "acl": {
        "owners": [
          "{{DATA_OWNERS_GROUP}}"
        ],
        "viewers": [
          "{{DATA_VIEWERS_GROUP}}"
        ]
      },
      "legal": {
        "legaltags": [
          "{{LEGAL_TAG}}"
        ],
        "otherRelevantDataCountries": [
          "{{ISO_3166_ALPHA_2_CODE}}"
        ]
      },
      "data": {
        "Name": "BGGM 2019",
        "ID": "BGGM2019",
        "Description": "British Geological Survey Global Geomagnetic Model 2019",
        "Code": "BGGM2019",
        "AttributionAuthority": "British Geological Survey (BGS)",
        "AttributionPublication": "https://geomag.bgs.ac.uk/data_service/directionaldrilling/bggm.html",
        "AttributionRevision": "2019",
        "Source": "Workbook ReferenceValues/Published/GeoMagneticModel.1.xlsx; commit SHA e3ae7f79.",
        "CommitDate": "2024-07-04T12:33:51+00:00"
      }
    },
    {
      "id": "{{NAMESPACE}}:reference-data--GeoMagneticModel:BGGM2020",
      "kind": "osdu:wks:reference-data--GeoMagneticModel:1.0.0",
      "acl": {
        "owners": [
          "{{DATA_OWNERS_GROUP}}"
        ],
        "viewers": [
          "{{DATA_VIEWERS_GROUP}}"
        ]
      },
      "legal": {
        "legaltags": [
          "{{LEGAL_TAG}}"
        ],
        "otherRelevantDataCountries": [
          "{{ISO_3166_ALPHA_2_CODE}}"
        ]
      },
      "data": {
        "Name": "BGGM 2020",
        "ID": "BGGM2020",
        "Description": "British Geological Survey Global Geomagnetic Model 2020",
        "Code": "BGGM2020",
        "AttributionAuthority": "British Geological Survey (BGS)",
        "AttributionPublication": "https://geomag.bgs.ac.uk/data_service/directionaldrilling/bggm.html",
        "AttributionRevision": "2020",
        "Source": "Workbook ReferenceValues/Published/GeoMagneticModel.1.xlsx; commit SHA e3ae7f79.",
        "CommitDate": "2024-07-04T12:33:51+00:00"
      }
    },
    {
      "id": "{{NAMESPACE}}:reference-data--GeoMagneticModel:BGGM2021",
      "kind": "osdu:wks:reference-data--GeoMagneticModel:1.0.0",
      "acl": {
        "owners": [
          "{{DATA_OWNERS_GROUP}}"
        ],
        "viewers": [
          "{{DATA_VIEWERS_GROUP}}"
        ]
      },
      "legal": {
        "legaltags": [
          "{{LEGAL_TAG}}"
        ],
        "otherRelevantDataCountries": [
          "{{ISO_3166_ALPHA_2_CODE}}"
        ]
      },
      "data": {
        "Name": "BGGM 2021",
        "ID": "BGGM2021",
        "Description": "British Geological Survey Global Geomagnetic Model 2021",
        "Code": "BGGM2021",
        "AttributionAuthority": "British Geological Survey (BGS)",
        "AttributionPublication": "https://geomag.bgs.ac.uk/data_service/directionaldrilling/bggm.html",
        "AttributionRevision": "2021",
        "Source": "Workbook ReferenceValues/Published/GeoMagneticModel.1.xlsx; commit SHA e3ae7f79.",
        "CommitDate": "2024-07-04T12:33:51+00:00"
      }
    },
    {
      "id": "{{NAMESPACE}}:reference-data--GeoMagneticModel:BGGM2022",
      "kind": "osdu:wks:reference-data--GeoMagneticModel:1.0.0",
      "acl": {
        "owners": [
          "{{DATA_OWNERS_GROUP}}"
        ],
        "viewers": [
          "{{DATA_VIEWERS_GROUP}}"
        ]
      },
      "legal": {
        "legaltags": [
          "{{LEGAL_TAG}}"
        ],
        "otherRelevantDataCountries": [
          "{{ISO_3166_ALPHA_2_CODE}}"
        ]
      },
      "data": {
        "Name": "BGGM 2022",
        "ID": "BGGM2022",
        "Description": "British Geological Survey Global Geomagnetic Model 2022",
        "Code": "BGGM2022",
        "AttributionAuthority": "British Geological Survey (BGS)",
        "AttributionPublication": "https://geomag.bgs.ac.uk/data_service/directionaldrilling/bggm.html",
        "AttributionRevision": "2022",
        "Source": "Workbook ReferenceValues/Published/GeoMagneticModel.1.xlsx; commit SHA e3ae7f79.",
        "CommitDate": "2024-07-04T12:33:51+00:00"
      }
    },
    {
      "id": "{{NAMESPACE}}:reference-data--GeoMagneticModel:BGGM2023",
      "kind": "osdu:wks:reference-data--GeoMagneticModel:1.0.0",
      "acl": {
        "owners": [
          "{{DATA_OWNERS_GROUP}}"
        ],
        "viewers": [
          "{{DATA_VIEWERS_GROUP}}"
        ]
      },
      "legal": {
        "legaltags": [
          "{{LEGAL_TAG}}"
        ],
        "otherRelevantDataCountries": [
          "{{ISO_3166_ALPHA_2_CODE}}"
        ]
      },
      "data": {
        "Name": "BGGM 2023",
        "ID": "BGGM2023",
        "Description": "British Geological Survey Global Geomagnetic Model 2023",
        "Code": "BGGM2023",
        "AttributionAuthority": "British Geological Survey (BGS)",
        "AttributionPublication": "https://geomag.bgs.ac.uk/data_service/directionaldrilling/bggm.html",
        "AttributionRevision": "2023",
        "Source": "Workbook ReferenceValues/Published/GeoMagneticModel.1.xlsx; commit SHA e3ae7f79.",
        "CommitDate": "2024-07-04T12:33:51+00:00"
      }
    },
    {
      "id": "{{NAMESPACE}}:reference-data--GeoMagneticModel:BGGM2024",
      "kind": "osdu:wks:reference-data--GeoMagneticModel:1.0.0",
      "acl": {
        "owners": [
          "{{DATA_OWNERS_GROUP}}"
        ],
        "viewers": [
          "{{DATA_VIEWERS_GROUP}}"
        ]
      },
      "legal": {
        "legaltags": [
          "{{LEGAL_TAG}}"
        ],
        "otherRelevantDataCountries": [
          "{{ISO_3166_ALPHA_2_CODE}}"
        ]
      },
      "data": {
        "Name": "BGGM 2024",
        "ID": "BGGM2024",
        "Description": "British Geological Survey Global Geomagnetic Model 2024",
        "Code": "BGGM2024",
        "AttributionAuthority": "British Geological Survey (BGS)",
        "AttributionPublication": "https://geomag.bgs.ac.uk/data_service/directionaldrilling/bggm.html",
        "AttributionRevision": "2024",
        "Source": "Workbook ReferenceValues/Published/GeoMagneticModel.1.xlsx; commit SHA e3ae7f79.",
        "CommitDate": "2024-07-04T12:33:51+00:00"
      }
    },
    {
      "id": "{{NAMESPACE}}:reference-data--GeoMagneticModel:HDGM2014",
      "kind": "osdu:wks:reference-data--GeoMagneticModel:1.0.0",
      "acl": {
        "owners": [
          "{{DATA_OWNERS_GROUP}}"
        ],
        "viewers": [
          "{{DATA_VIEWERS_GROUP}}"
        ]
      },
      "legal": {
        "legaltags": [
          "{{LEGAL_TAG}}"
        ],
        "otherRelevantDataCountries": [
          "{{ISO_3166_ALPHA_2_CODE}}"
        ]
      },
      "data": {
        "Name": "HDGM-2014",
        "ID": "HDGM2014",
        "Description": "High Definition Geomagnetic Model 2014",
        "Code": "HDGM2014",
        "AttributionAuthority": "US NCEI NOAA",
        "AttributionPublication": "https://www.ncei.noaa.gov/products/high-definition-geomagnetic-model",
        "AttributionRevision": "2014",
        "Source": "Workbook ReferenceValues/Published/GeoMagneticModel.1.xlsx; commit SHA e3ae7f79.",
        "CommitDate": "2024-07-04T12:33:51+00:00"
      }
    },
    {
      "id": "{{NAMESPACE}}:reference-data--GeoMagneticModel:HDGM2015",
      "kind": "osdu:wks:reference-data--GeoMagneticModel:1.0.0",
      "acl": {
        "owners": [
          "{{DATA_OWNERS_GROUP}}"
        ],
        "viewers": [
          "{{DATA_VIEWERS_GROUP}}"
        ]
      },
      "legal": {
        "legaltags": [
          "{{LEGAL_TAG}}"
        ],
        "otherRelevantDataCountries": [
          "{{ISO_3166_ALPHA_2_CODE}}"
        ]
      },
      "data": {
        "Name": "HDGM-2015",
        "ID": "HDGM2015",
        "Description": "High Definition Geomagnetic Model 2015",
        "Code": "HDGM2015",
        "AttributionAuthority": "US NCEI NOAA",
        "AttributionPublication": "https://www.ncei.noaa.gov/products/high-definition-geomagnetic-model",
        "AttributionRevision": "2015",
        "Source": "Workbook ReferenceValues/Published/GeoMagneticModel.1.xlsx; commit SHA e3ae7f79.",
        "CommitDate": "2024-07-04T12:33:51+00:00"
      }
    },
    {
      "id": "{{NAMESPACE}}:reference-data--GeoMagneticModel:HDGM2016",
      "kind": "osdu:wks:reference-data--GeoMagneticModel:1.0.0",
      "acl": {
        "owners": [
          "{{DATA_OWNERS_GROUP}}"
        ],
        "viewers": [
          "{{DATA_VIEWERS_GROUP}}"
        ]
      },
      "legal": {
        "legaltags": [
          "{{LEGAL_TAG}}"
        ],
        "otherRelevantDataCountries": [
          "{{ISO_3166_ALPHA_2_CODE}}"
        ]
      },
      "data": {
        "Name": "HDGM-2016",
        "ID": "HDGM2016",
        "Description": "High Definition Geomagnetic Model 2016",
        "Code": "HDGM2016",
        "AttributionAuthority": "US NCEI NOAA",
        "AttributionPublication": "https://www.ncei.noaa.gov/products/high-definition-geomagnetic-model",
        "AttributionRevision": "2016",
        "Source": "Workbook ReferenceValues/Published/GeoMagneticModel.1.xlsx; commit SHA e3ae7f79.",
        "CommitDate": "2024-07-04T12:33:51+00:00"
      }
    },
    {
      "id": "{{NAMESPACE}}:reference-data--GeoMagneticModel:HDGM2017",
      "kind": "osdu:wks:reference-data--GeoMagneticModel:1.0.0",
      "acl": {
        "owners": [
          "{{DATA_OWNERS_GROUP}}"
        ],
        "viewers": [
          "{{DATA_VIEWERS_GROUP}}"
        ]
      },
      "legal": {
        "legaltags": [
          "{{LEGAL_TAG}}"
        ],
        "otherRelevantDataCountries": [
          "{{ISO_3166_ALPHA_2_CODE}}"
        ]
      },
      "data": {
        "Name": "HDGM-2017",
        "ID": "HDGM2017",
        "Description": "High Definition Geomagnetic Model 2017",
        "Code": "HDGM2017",
        "AttributionAuthority": "US NCEI NOAA",
        "AttributionPublication": "https://www.ncei.noaa.gov/products/high-definition-geomagnetic-model",
        "AttributionRevision": "2017",
        "Source": "Workbook ReferenceValues/Published/GeoMagneticModel.1.xlsx; commit SHA e3ae7f79.",
        "CommitDate": "2024-07-04T12:33:51+00:00"
      }
    },
    {
      "id": "{{NAMESPACE}}:reference-data--GeoMagneticModel:HDGM2018",
      "kind": "osdu:wks:reference-data--GeoMagneticModel:1.0.0",
      "acl": {
        "owners": [
          "{{DATA_OWNERS_GROUP}}"
        ],
        "viewers": [
          "{{DATA_VIEWERS_GROUP}}"
        ]
      },
      "legal": {
        "legaltags": [
          "{{LEGAL_TAG}}"
        ],
        "otherRelevantDataCountries": [
          "{{ISO_3166_ALPHA_2_CODE}}"
        ]
      },
      "data": {
        "Name": "HDGM-2018",
        "ID": "HDGM2018",
        "Description": "High Definition Geomagnetic Model 2018",
        "Code": "HDGM2018",
        "AttributionAuthority": "US NCEI NOAA",
        "AttributionPublication": "https://www.ncei.noaa.gov/products/high-definition-geomagnetic-model",
        "AttributionRevision": "2018",
        "Source": "Workbook ReferenceValues/Published/GeoMagneticModel.1.xlsx; commit SHA e3ae7f79.",
        "CommitDate": "2024-07-04T12:33:51+00:00"
      }
    },
    {
      "id": "{{NAMESPACE}}:reference-data--GeoMagneticModel:HDGM2019",
      "kind": "osdu:wks:reference-data--GeoMagneticModel:1.0.0",
      "acl": {
        "owners": [
          "{{DATA_OWNERS_GROUP}}"
        ],
        "viewers": [
          "{{DATA_VIEWERS_GROUP}}"
        ]
      },
      "legal": {
        "legaltags": [
          "{{LEGAL_TAG}}"
        ],
        "otherRelevantDataCountries": [
          "{{ISO_3166_ALPHA_2_CODE}}"
        ]
      },
      "data": {
        "Name": "HDGM-2019",
        "ID": "HDGM2019",
        "Description": "High Definition Geomagnetic Model 2019",
        "Code": "HDGM2019",
        "AttributionAuthority": "US NCEI NOAA",
        "AttributionPublication": "https://www.ncei.noaa.gov/products/high-definition-geomagnetic-model",
        "AttributionRevision": "2019",
        "Source": "Workbook ReferenceValues/Published/GeoMagneticModel.1.xlsx; commit SHA e3ae7f79.",
        "CommitDate": "2024-07-04T12:33:51+00:00"
      }
    },
    {
      "id": "{{NAMESPACE}}:reference-data--GeoMagneticModel:HDGM2020",
      "kind": "osdu:wks:reference-data--GeoMagneticModel:1.0.0",
      "acl": {
        "owners": [
          "{{DATA_OWNERS_GROUP}}"
        ],
        "viewers": [
          "{{DATA_VIEWERS_GROUP}}"
        ]
      },
      "legal": {
        "legaltags": [
          "{{LEGAL_TAG}}"
        ],
        "otherRelevantDataCountries": [
          "{{ISO_3166_ALPHA_2_CODE}}"
        ]
      },
      "data": {
        "Name": "HDGM-2020",
        "ID": "HDGM2020",
        "Description": "High Definition Geomagnetic Model 2020",
        "Code": "HDGM2020",
        "AttributionAuthority": "US NCEI NOAA",
        "AttributionPublication": "https://www.ncei.noaa.gov/products/high-definition-geomagnetic-model",
        "AttributionRevision": "2020",
        "Source": "Workbook ReferenceValues/Published/GeoMagneticModel.1.xlsx; commit SHA e3ae7f79.",
        "CommitDate": "2024-07-04T12:33:51+00:00"
      }
    },
    {
      "id": "{{NAMESPACE}}:reference-data--GeoMagneticModel:HDGM2021",
      "kind": "osdu:wks:reference-data--GeoMagneticModel:1.0.0",
      "acl": {
        "owners": [
          "{{DATA_OWNERS_GROUP}}"
        ],
        "viewers": [
          "{{DATA_VIEWERS_GROUP}}"
        ]
      },
      "legal": {
        "legaltags": [
          "{{LEGAL_TAG}}"
        ],
        "otherRelevantDataCountries": [
          "{{ISO_3166_ALPHA_2_CODE}}"
        ]
      },
      "data": {
        "Name": "HDGM-2021",
        "ID": "HDGM2021",
        "Description": "High Definition Geomagnetic Model 2021",
        "Code": "HDGM2021",
        "AttributionAuthority": "US NCEI NOAA",
        "AttributionPublication": "https://www.ncei.noaa.gov/products/high-definition-geomagnetic-model",
        "AttributionRevision": "2021",
        "Source": "Workbook ReferenceValues/Published/GeoMagneticModel.1.xlsx; commit SHA e3ae7f79.",
        "CommitDate": "2024-07-04T12:33:51+00:00"
      }
    },
    {
      "id": "{{NAMESPACE}}:reference-data--GeoMagneticModel:HDGM2022",
      "kind": "osdu:wks:reference-data--GeoMagneticModel:1.0.0",
      "acl": {
        "owners": [
          "{{DATA_OWNERS_GROUP}}"
        ],
        "viewers": [
          "{{DATA_VIEWERS_GROUP}}"
        ]
      },
      "legal": {
        "legaltags": [
          "{{LEGAL_TAG}}"
        ],
        "otherRelevantDataCountries": [
          "{{ISO_3166_ALPHA_2_CODE}}"
        ]
      },
      "data": {
        "Name": "HDGM-2022",
        "ID": "HDGM2022",
        "Description": "High Definition Geomagnetic Model 2022",
        "Code": "HDGM2022",
        "AttributionAuthority": "US NCEI NOAA",
        "AttributionPublication": "https://www.ncei.noaa.gov/products/high-definition-geomagnetic-model",
        "AttributionRevision": "2022",
        "Source": "Workbook ReferenceValues/Published/GeoMagneticModel.1.xlsx; commit SHA e3ae7f79.",
        "CommitDate": "2024-07-04T12:33:51+00:00"
      }
    },
    {
      "id": "{{NAMESPACE}}:reference-data--GeoMagneticModel:HDGM2023",
      "kind": "osdu:wks:reference-data--GeoMagneticModel:1.0.0",
      "acl": {
        "owners": [
          "{{DATA_OWNERS_GROUP}}"
        ],
        "viewers": [
          "{{DATA_VIEWERS_GROUP}}"
        ]
      },
      "legal": {
        "legaltags": [
          "{{LEGAL_TAG}}"
        ],
        "otherRelevantDataCountries": [
          "{{ISO_3166_ALPHA_2_CODE}}"
        ]
      },
      "data": {
        "Name": "HDGM-2023",
        "ID": "HDGM2023",
        "Description": "High Definition Geomagnetic Model 2023",
        "Code": "HDGM2023",
        "AttributionAuthority": "US NCEI NOAA",
        "AttributionPublication": "https://www.ncei.noaa.gov/products/high-definition-geomagnetic-model",
        "AttributionRevision": "2023",
        "Source": "Workbook ReferenceValues/Published/GeoMagneticModel.1.xlsx; commit SHA e3ae7f79.",
        "CommitDate": "2024-07-04T12:33:51+00:00"
      }
    },
    {
      "id": "{{NAMESPACE}}:reference-data--GeoMagneticModel:HDGM2024",
      "kind": "osdu:wks:reference-data--GeoMagneticModel:1.0.0",
      "acl": {
        "owners": [
          "{{DATA_OWNERS_GROUP}}"
        ],
        "viewers": [
          "{{DATA_VIEWERS_GROUP}}"
        ]
      },
      "legal": {
        "legaltags": [
          "{{LEGAL_TAG}}"
        ],
        "otherRelevantDataCountries": [
          "{{ISO_3166_ALPHA_2_CODE}}"
        ]
      },
      "data": {
        "Name": "HDGM-2024",
        "ID": "HDGM2024",
        "Description": "High Definition Geomagnetic Model 2024",
        "Code": "HDGM2024",
        "AttributionAuthority": "US NCEI NOAA",
        "AttributionPublication": "https://www.ncei.noaa.gov/products/high-definition-geomagnetic-model",
        "AttributionRevision": "2024",
        "Source": "Workbook ReferenceValues/Published/GeoMagneticModel.1.xlsx; commit SHA e3ae7f79.",
        "CommitDate": "2024-07-04T12:33:51+00:00"
      }
    },
    {
      "id": "{{NAMESPACE}}:reference-data--GeoMagneticModel:HDGM",
      "kind": "osdu:wks:reference-data--GeoMagneticModel:1.0.0",
      "acl": {
        "owners": [
          "{{DATA_OWNERS_GROUP}}"
        ],
        "viewers": [
          "{{DATA_VIEWERS_GROUP}}"
        ]
      },
      "legal": {
        "legaltags": [
          "{{LEGAL_TAG}}"
        ],
        "otherRelevantDataCountries": [
          "{{ISO_3166_ALPHA_2_CODE}}"
        ]
      },
      "data": {
        "Name": "HDGM",
        "ID": "HDGM",
        "Description": "High Definition Geomagnetic Model (Undifferentiated)",
        "Code": "HDGM",
        "AttributionAuthority": "US NCEI NOAA",
        "AttributionPublication": "https://www.ncei.noaa.gov/products/high-definition-geomagnetic-model",
        "Source": "Workbook ReferenceValues/Published/GeoMagneticModel.1.xlsx; commit SHA e3ae7f79.",
        "CommitDate": "2024-07-04T12:33:51+00:00"
      }
    },
    {
      "id": "{{NAMESPACE}}:reference-data--GeoMagneticModel:WMM_95",
      "kind": "osdu:wks:reference-data--GeoMagneticModel:1.0.0",
      "acl": {
        "owners": [
          "{{DATA_OWNERS_GROUP}}"
        ],
        "viewers": [
          "{{DATA_VIEWERS_GROUP}}"
        ]
      },
      "legal": {
        "legaltags": [
          "{{LEGAL_TAG}}"
        ],
        "otherRelevantDataCountries": [
          "{{ISO_3166_ALPHA_2_CODE}}"
        ]
      },
      "data": {
        "Name": "WMM 1995",
        "ID": "WMM_95",
        "Description": "World Magnetic Model 1995",
        "Code": "WMM_95",
        "AttributionAuthority": "BGS, US NCEI NOAA",
        "AttributionPublication": "https://www.ngdc.noaa.gov/geomag/WMM/data/WMMReports/WMM_BR95.pdf",
        "AttributionRevision": "1995",
        "Source": "Workbook ReferenceValues/Published/GeoMagneticModel.1.xlsx; commit SHA e3ae7f79.",
        "CommitDate": "2024-07-04T12:33:51+00:00"
      }
    },
    {
      "id": "{{NAMESPACE}}:reference-data--GeoMagneticModel:WMM_2000",
      "kind": "osdu:wks:reference-data--GeoMagneticModel:1.0.0",
      "acl": {
        "owners": [
          "{{DATA_OWNERS_GROUP}}"
        ],
        "viewers": [
          "{{DATA_VIEWERS_GROUP}}"
        ]
      },
      "legal": {
        "legaltags": [
          "{{LEGAL_TAG}}"
        ],
        "otherRelevantDataCountries": [
          "{{ISO_3166_ALPHA_2_CODE}}"
        ]
      },
      "data": {
        "Name": "WMM 2000",
        "ID": "WMM_2000",
        "Description": "World Magnetic Model 2000",
        "Code": "WMM_2000",
        "AttributionAuthority": "BGS, US NCEI NOAA",
        "AttributionPublication": "https://www.ngdc.noaa.gov/geomag/WMM/data/WMMReports/wmm2000.pdf",
        "AttributionRevision": "2000",
        "Source": "Workbook ReferenceValues/Published/GeoMagneticModel.1.xlsx; commit SHA e3ae7f79.",
        "CommitDate": "2024-07-04T12:33:51+00:00"
      }
    },
    {
      "id": "{{NAMESPACE}}:reference-data--GeoMagneticModel:WMM_2005",
      "kind": "osdu:wks:reference-data--GeoMagneticModel:1.0.0",
      "acl": {
        "owners": [
          "{{DATA_OWNERS_GROUP}}"
        ],
        "viewers": [
          "{{DATA_VIEWERS_GROUP}}"
        ]
      },
      "legal": {
        "legaltags": [
          "{{LEGAL_TAG}}"
        ],
        "otherRelevantDataCountries": [
          "{{ISO_3166_ALPHA_2_CODE}}"
        ]
      },
      "data": {
        "Name": "WMM 2005",
        "ID": "WMM_2005",
        "Description": "World Magnetic Model 2005",
        "Code": "WMM_2005",
        "AttributionAuthority": "BGS, US NCEI NOAA",
        "AttributionPublication": "https://www.ngdc.noaa.gov/geomag/WMM/data/WMMReports/TRWMM_2005.pdf",
        "AttributionRevision": "2005",
        "Source": "Workbook ReferenceValues/Published/GeoMagneticModel.1.xlsx; commit SHA e3ae7f79.",
        "CommitDate": "2024-07-04T12:33:51+00:00"
      }
    },
    {
      "id": "{{NAMESPACE}}:reference-data--GeoMagneticModel:WMM2010",
      "kind": "osdu:wks:reference-data--GeoMagneticModel:1.0.0",
      "acl": {
        "owners": [
          "{{DATA_OWNERS_GROUP}}"
        ],
        "viewers": [
          "{{DATA_VIEWERS_GROUP}}"
        ]
      },
      "legal": {
        "legaltags": [
          "{{LEGAL_TAG}}"
        ],
        "otherRelevantDataCountries": [
          "{{ISO_3166_ALPHA_2_CODE}}"
        ]
      },
      "data": {
        "Name": "WMM 2010",
        "ID": "WMM2010",
        "Description": "World Magnetic Model 2010",
        "Code": "WMM2010",
        "AttributionAuthority": "BGS, US NCEI NOAA",
        "AttributionPublication": "https://www.ngdc.noaa.gov/geomag/WMM/data/WMMReports/WMM2010_Report.pdf",
        "AttributionRevision": "2010",
        "Source": "Workbook ReferenceValues/Published/GeoMagneticModel.1.xlsx; commit SHA e3ae7f79.",
        "CommitDate": "2024-07-04T12:33:51+00:00"
      }
    },
    {
      "id": "{{NAMESPACE}}:reference-data--GeoMagneticModel:WMM2015",
      "kind": "osdu:wks:reference-data--GeoMagneticModel:1.0.0",
      "acl": {
        "owners": [
          "{{DATA_OWNERS_GROUP}}"
        ],
        "viewers": [
          "{{DATA_VIEWERS_GROUP}}"
        ]
      },
      "legal": {
        "legaltags": [
          "{{LEGAL_TAG}}"
        ],
        "otherRelevantDataCountries": [
          "{{ISO_3166_ALPHA_2_CODE}}"
        ]
      },
      "data": {
        "Name": "WMM 2015",
        "ID": "WMM2015",
        "Description": "World Magnetic Model 2015",
        "Code": "WMM2015",
        "AttributionAuthority": "BGS, US NCEI NOAA",
        "AttributionPublication": "https://www.ngdc.noaa.gov/geomag/WMM/data/WMMReports/WMM2015_Report.pdf",
        "AttributionRevision": "2015",
        "Source": "Workbook ReferenceValues/Published/GeoMagneticModel.1.xlsx; commit SHA e3ae7f79.",
        "CommitDate": "2024-07-04T12:33:51+00:00"
      }
    },
    {
      "id": "{{NAMESPACE}}:reference-data--GeoMagneticModel:WMM2020",
      "kind": "osdu:wks:reference-data--GeoMagneticModel:1.0.0",
      "acl": {
        "owners": [
          "{{DATA_OWNERS_GROUP}}"
        ],
        "viewers": [
          "{{DATA_VIEWERS_GROUP}}"
        ]
      },
      "legal": {
        "legaltags": [
          "{{LEGAL_TAG}}"
        ],
        "otherRelevantDataCountries": [
          "{{ISO_3166_ALPHA_2_CODE}}"
        ]
      },
      "data": {
        "Name": "WMM 2020",
        "ID": "WMM2020",
        "Description": "World Magnetic Model 2020",
        "Code": "WMM2020",
        "AttributionAuthority": "BGS, US NCEI NOAA, US NGA",
        "AttributionPublication": "https://www.ncei.noaa.gov/products/world-magnetic-model, https://www.nga.mil/resources/World_Magnetic_Model_2020.html",
        "AttributionRevision": "2020",
        "Source": "Workbook ReferenceValues/Published/GeoMagneticModel.1.xlsx; commit SHA e3ae7f79.",
        "CommitDate": "2024-07-04T12:33:51+00:00"
      }
    },
    {
      "id": "{{NAMESPACE}}:reference-data--GeoMagneticModel:IGRF90",
      "kind": "osdu:wks:reference-data--GeoMagneticModel:1.0.0",
      "acl": {
        "owners": [
          "{{DATA_OWNERS_GROUP}}"
        ],
        "viewers": [
          "{{DATA_VIEWERS_GROUP}}"
        ]
      },
      "legal": {
        "legaltags": [
          "{{LEGAL_TAG}}"
        ],
        "otherRelevantDataCountries": [
          "{{ISO_3166_ALPHA_2_CODE}}"
        ]
      },
      "data": {
        "Name": "IGRF 1990",
        "ID": "IGRF90",
        "Description": "International Geomagnetic Reference Field 1990 (IGRF-6)",
        "Code": "IGRF90",
        "AttributionAuthority": "IAGA",
        "AttributionPublication": "https://www.ngdc.noaa.gov/IAGA/vmod/prevmodels/IGRFGEN6.DAT",
        "AttributionRevision": "1990",
        "Source": "Workbook ReferenceValues/Published/GeoMagneticModel.1.xlsx; commit SHA e3ae7f79.",
        "CommitDate": "2024-07-04T12:33:51+00:00"
      }
    },
    {
      "id": "{{NAMESPACE}}:reference-data--GeoMagneticModel:IGRF95",
      "kind": "osdu:wks:reference-data--GeoMagneticModel:1.0.0",
      "acl": {
        "owners": [
          "{{DATA_OWNERS_GROUP}}"
        ],
        "viewers": [
          "{{DATA_VIEWERS_GROUP}}"
        ]
      },
      "legal": {
        "legaltags": [
          "{{LEGAL_TAG}}"
        ],
        "otherRelevantDataCountries": [
          "{{ISO_3166_ALPHA_2_CODE}}"
        ]
      },
      "data": {
        "Name": "IGRF 1995",
        "ID": "IGRF95",
        "Description": "International Geomagnetic Reference Field 1995 (IGRF-7)",
        "Code": "IGRF95",
        "AttributionAuthority": "IAGA",
        "AttributionPublication": "https://www.ngdc.noaa.gov/IAGA/vmod/prevmodels/IGRFGEN7.DAT",
        "AttributionRevision": "1995",
        "Source": "Workbook ReferenceValues/Published/GeoMagneticModel.1.xlsx; commit SHA e3ae7f79.",
        "CommitDate": "2024-07-04T12:33:51+00:00"
      }
    },
    {
      "id": "{{NAMESPACE}}:reference-data--GeoMagneticModel:IGRF2000",
      "kind": "osdu:wks:reference-data--GeoMagneticModel:1.0.0",
      "acl": {
        "owners": [
          "{{DATA_OWNERS_GROUP}}"
        ],
        "viewers": [
          "{{DATA_VIEWERS_GROUP}}"
        ]
      },
      "legal": {
        "legaltags": [
          "{{LEGAL_TAG}}"
        ],
        "otherRelevantDataCountries": [
          "{{ISO_3166_ALPHA_2_CODE}}"
        ]
      },
      "data": {
        "Name": "IGRF 2000",
        "ID": "IGRF2000",
        "Description": "International Geomagnetic Reference Field 2000 (IGRF-8)",
        "Code": "IGRF2000",
        "AttributionAuthority": "IAGA",
        "AttributionPublication": "https://www.ngdc.noaa.gov/IAGA/vmod/prevmodels/IGRFGEN8.DAT",
        "AttributionRevision": "2000",
        "Source": "Workbook ReferenceValues/Published/GeoMagneticModel.1.xlsx; commit SHA e3ae7f79.",
        "CommitDate": "2024-07-04T12:33:51+00:00"
      }
    },
    {
      "id": "{{NAMESPACE}}:reference-data--GeoMagneticModel:IGRF2005",
      "kind": "osdu:wks:reference-data--GeoMagneticModel:1.0.0",
      "acl": {
        "owners": [
          "{{DATA_OWNERS_GROUP}}"
        ],
        "viewers": [
          "{{DATA_VIEWERS_GROUP}}"
        ]
      },
      "legal": {
        "legaltags": [
          "{{LEGAL_TAG}}"
        ],
        "otherRelevantDataCountries": [
          "{{ISO_3166_ALPHA_2_CODE}}"
        ]
      },
      "data": {
        "Name": "IGRF 2005",
        "ID": "IGRF2005",
        "Description": "International Geomagnetic Reference Field 2005 (IGRF-10)",
        "Code": "IGRF2005",
        "AttributionAuthority": "IAGA",
        "AttributionPublication": "https://www.ngdc.noaa.gov/IAGA/vmod/coeffs/igrf10coeffs.txt",
        "AttributionRevision": "2005",
        "Source": "Workbook ReferenceValues/Published/GeoMagneticModel.1.xlsx; commit SHA e3ae7f79.",
        "CommitDate": "2024-07-04T12:33:51+00:00"
      }
    },
    {
      "id": "{{NAMESPACE}}:reference-data--GeoMagneticModel:IGRF2010",
      "kind": "osdu:wks:reference-data--GeoMagneticModel:1.0.0",
      "acl": {
        "owners": [
          "{{DATA_OWNERS_GROUP}}"
        ],
        "viewers": [
          "{{DATA_VIEWERS_GROUP}}"
        ]
      },
      "legal": {
        "legaltags": [
          "{{LEGAL_TAG}}"
        ],
        "otherRelevantDataCountries": [
          "{{ISO_3166_ALPHA_2_CODE}}"
        ]
      },
      "data": {
        "Name": "IGRF 2010",
        "ID": "IGRF2010",
        "Description": "International Geomagnetic Reference Field 2010 (IGRF-11)",
        "Code": "IGRF2010",
        "AttributionAuthority": "IAGA",
        "AttributionPublication": "https://www.ngdc.noaa.gov/IAGA/vmod/coeffs/igrf11coeffs.txt",
        "AttributionRevision": "2010",
        "Source": "Workbook ReferenceValues/Published/GeoMagneticModel.1.xlsx; commit SHA e3ae7f79.",
        "CommitDate": "2024-07-04T12:33:51+00:00"
      }
    },
    {
      "id": "{{NAMESPACE}}:reference-data--GeoMagneticModel:IGRF2015",
      "kind": "osdu:wks:reference-data--GeoMagneticModel:1.0.0",
      "acl": {
        "owners": [
          "{{DATA_OWNERS_GROUP}}"
        ],
        "viewers": [
          "{{DATA_VIEWERS_GROUP}}"
        ]
      },
      "legal": {
        "legaltags": [
          "{{LEGAL_TAG}}"
        ],
        "otherRelevantDataCountries": [
          "{{ISO_3166_ALPHA_2_CODE}}"
        ]
      },
      "data": {
        "Name": "IGRF 2015",
        "ID": "IGRF2015",
        "Description": "International Geomagnetic Reference Field 2015 (IGRF-12)",
        "Code": "IGRF2015",
        "AttributionAuthority": "IAGA",
        "AttributionPublication": "https://www.ngdc.noaa.gov/IAGA/vmod/coeffs/igrf12coeffs.txt",
        "AttributionRevision": "2015",
        "Source": "Workbook ReferenceValues/Published/GeoMagneticModel.1.xlsx; commit SHA e3ae7f79.",
        "CommitDate": "2024-07-04T12:33:51+00:00"
      }
    },
    {
      "id": "{{NAMESPACE}}:reference-data--GeoMagneticModel:IGRF2020",
      "kind": "osdu:wks:reference-data--GeoMagneticModel:1.0.0",
      "acl": {
        "owners": [
          "{{DATA_OWNERS_GROUP}}"
        ],
        "viewers": [
          "{{DATA_VIEWERS_GROUP}}"
        ]
      },
      "legal": {
        "legaltags": [
          "{{LEGAL_TAG}}"
        ],
        "otherRelevantDataCountries": [
          "{{ISO_3166_ALPHA_2_CODE}}"
        ]
      },
      "data": {
        "Name": "IGRF 2020",
        "ID": "IGRF2020",
        "Description": "International Geomagnetic Reference Field 2020 (IGRF-13)",
        "Code": "IGRF2020",
        "AttributionAuthority": "IAGA",
        "AttributionPublication": "https://www.ngdc.noaa.gov/IAGA/vmod/igrf.html, https://www.ngdc.noaa.gov/IAGA/vmod/coeffs/igrf13coeffs.txt",
        "AttributionRevision": "2020",
        "Source": "Workbook ReferenceValues/Published/GeoMagneticModel.1.xlsx; commit SHA e3ae7f79.",
        "CommitDate": "2024-07-04T12:33:51+00:00"
      }
    },
    {
      "id": "{{NAMESPACE}}:reference-data--GeoMagneticModel:UserDefined",
      "kind": "osdu:wks:reference-data--GeoMagneticModel:1.0.0",
      "acl": {
        "owners": [
          "{{DATA_OWNERS_GROUP}}"
        ],
        "viewers": [
          "{{DATA_VIEWERS_GROUP}}"
        ]
      },
      "legal": {
        "legaltags": [
          "{{LEGAL_TAG}}"
        ],
        "otherRelevantDataCountries": [
          "{{ISO_3166_ALPHA_2_CODE}}"
        ]
      },
      "data": {
        "Name": "User Defined",
        "ID": "UserDefined",
        "Description": "User Defined",
        "Code": "UserDefined",
        "Source": "Workbook ReferenceValues/Published/GeoMagneticModel.1.xlsx; commit SHA e3ae7f79.",
        "CommitDate": "2024-07-04T12:33:51+00:00"
      }
    }
  ]
}