{"kind":"osdu:wks:Manifest:1.0.0","ReferenceData":[{"id":"{{NAMESPACE}}:reference-data--PropertyNameType:V0","kind":"osdu:wks:reference-data--PropertyNameType:1.0.0","acl":{"owners":["{{DATA_OWNERS_GROUP}}"],"viewers":["{{DATA_VIEWERS_GROUP}}"]},"legal":{"legaltags":["{{LEGAL_TAG}}"],"otherRelevantDataCountries":["{{ISO_3166_ALPHA_2_CODE}}"]},"data":{"Name":"V0","Description":"Velocity parameter - zero offset","Code":"V0","Source":"Workbook ReferenceValues/Published/PropertyNameType.1.xlsx; commit SHA 56f7c736.","CommitDate":"2024-02-09T16:51:15+00:00"}},{"id":"{{NAMESPACE}}:reference-data--PropertyNameType:Vnmo","kind":"osdu:wks:reference-data--PropertyNameType:1.0.0","acl":{"owners":["{{DATA_OWNERS_GROUP}}"],"viewers":["{{DATA_VIEWERS_GROUP}}"]},"legal":{"legaltags":["{{LEGAL_TAG}}"],"otherRelevantDataCountries":["{{ISO_3166_ALPHA_2_CODE}}"]},"data":{"Name":"Vnmo","Description":"Velocity parameter - hyperbolic moveout","Code":"Vnmo","Source":"Workbook ReferenceValues/Published/PropertyNameType.1.xlsx; commit SHA 56f7c736.","CommitDate":"2024-02-09T16:51:15+00:00"}},{"id":"{{NAMESPACE}}:reference-data--PropertyNameType:Vp","kind":"osdu:wks:reference-data--PropertyNameType:1.0.0","acl":{"owners":["{{DATA_OWNERS_GROUP}}"],"viewers":["{{DATA_VIEWERS_GROUP}}"]},"legal":{"legaltags":["{{LEGAL_TAG}}"],"otherRelevantDataCountries":["{{ISO_3166_ALPHA_2_CODE}}"]},"data":{"Name":"Vp","Description":"Velocity parameter - primary wave group velocity","Code":"Vp","Source":"Workbook ReferenceValues/Published/PropertyNameType.1.xlsx; commit SHA 56f7c736.","CommitDate":"2024-02-09T16:51:15+00:00"}},{"id":"{{NAMESPACE}}:reference-data--PropertyNameType:Vs","kind":"osdu:wks:reference-data--PropertyNameType:1.0.0","acl":{"owners":["{{DATA_OWNERS_GROUP}}"],"viewers":["{{DATA_VIEWERS_GROUP}}"]},"legal":{"legaltags":["{{LEGAL_TAG}}"],"otherRelevantDataCountries":["{{ISO_3166_ALPHA_2_CODE}}"]},"data":{"Name":"Vs","Description":"Velocity parameter - shear wave group velocity","Code":"Vs","Source":"Workbook ReferenceValues/Published/PropertyNameType.1.xlsx; commit SHA 56f7c736.","CommitDate":"2024-02-09T16:51:15+00:00"}},{"id":"{{NAMESPACE}}:reference-data--PropertyNameType:Delta","kind":"osdu:wks:reference-data--PropertyNameType:1.0.0","acl":{"owners":["{{DATA_OWNERS_GROUP}}"],"viewers":["{{DATA_VIEWERS_GROUP}}"]},"legal":{"legaltags":["{{LEGAL_TAG}}"],"otherRelevantDataCountries":["{{ISO_3166_ALPHA_2_CODE}}"]},"data":{"Name":"Delta","Description":"Anisotropy parameter - near offset ","Code":"Delta","Source":"Workbook ReferenceValues/Published/PropertyNameType.1.xlsx; commit SHA 56f7c736.","CommitDate":"2024-02-09T16:51:15+00:00"}},{"id":"{{NAMESPACE}}:reference-data--PropertyNameType:Eta","kind":"osdu:wks:reference-data--PropertyNameType:1.0.0","acl":{"owners":["{{DATA_OWNERS_GROUP}}"],"viewers":["{{DATA_VIEWERS_GROUP}}"]},"legal":{"legaltags":["{{LEGAL_TAG}}"],"otherRelevantDataCountries":["{{ISO_3166_ALPHA_2_CODE}}"]},"data":{"Name":"Eta","Description":"Anisotropy parameter - long offset deviation from nmo","Code":"Eta","Source":"Workbook ReferenceValues/Published/PropertyNameType.1.xlsx; commit SHA 56f7c736.","CommitDate":"2024-02-09T16:51:15+00:00"}},{"id":"{{NAMESPACE}}:reference-data--PropertyNameType:Epsilon","kind":"osdu:wks:reference-data--PropertyNameType:1.0.0","acl":{"owners":["{{DATA_OWNERS_GROUP}}"],"viewers":["{{DATA_VIEWERS_GROUP}}"]},"legal":{"legaltags":["{{LEGAL_TAG}}"],"otherRelevantDataCountries":["{{ISO_3166_ALPHA_2_CODE}}"]},"data":{"Name":"Epsilon","Description":"Anisotropy parameter - horizontal versus vertical difference","Code":"Epsilon","Source":"Workbook ReferenceValues/Published/PropertyNameType.1.xlsx; commit SHA 56f7c736.","CommitDate":"2024-02-09T16:51:15+00:00"}}]}