{
  "kind": "osdu:wks:Manifest:1.0.0",
  "ReferenceData": [
    {
      "id": "{{NAMESPACE}}:reference-data--SampleStressLoadingStage:Loading",
      "kind": "osdu:wks:reference-data--SampleStressLoadingStage:1.0.0",
      "acl": {
        "owners": [
          "{{DATA_OWNERS_GROUP}}"
        ],
        "viewers": [
          "{{DATA_VIEWERS_GROUP}}"
        ]
      },
      "legal": {
        "legaltags": [
          "{{LEGAL_TAG}}"
        ],
        "otherRelevantDataCountries": [
          "{{ISO_3166_ALPHA_2_CODE}}"
        ]
      },
      "data": {
        "Name": "Loading",
        "ID": "Loading",
        "Description": "Stress is being actively applied to the sample.",
        "Code": "Loading",
        "Source": "Workbook ReferenceValues/Published/SampleStressLoadingStage.1.xlsx; commit SHA 08e1c4c5.",
        "CommitDate": "2025-02-09T17:44:00+00:00"
      }
    },
    {
      "id": "{{NAMESPACE}}:reference-data--SampleStressLoadingStage:Unloading",
      "kind": "osdu:wks:reference-data--SampleStressLoadingStage:1.0.0",
      "acl": {
        "owners": [
          "{{DATA_OWNERS_GROUP}}"
        ],
        "viewers": [
          "{{DATA_VIEWERS_GROUP}}"
        ]
      },
      "legal": {
        "legaltags": [
          "{{LEGAL_TAG}}"
        ],
        "otherRelevantDataCountries": [
          "{{ISO_3166_ALPHA_2_CODE}}"
        ]
      },
      "data": {
        "Name": "Unloading",
        "ID": "Unloading",
        "Description": "Stress is being removed from the sample.",
        "Code": "Unloading",
        "Source": "Workbook ReferenceValues/Published/SampleStressLoadingStage.1.xlsx; commit SHA 08e1c4c5.",
        "CommitDate": "2025-02-09T17:44:00+00:00"
      }
    }
  ]
}