{"kind":"osdu:wks:Manifest:1.0.0","ReferenceData":[{"id":"{{NAMESPACE}}:reference-data--SeismicFaultType:Normal","kind":"osdu:wks:reference-data--SeismicFaultType:1.0.1","acl":{"owners":["{{DATA_OWNERS_GROUP}}"],"viewers":["{{DATA_VIEWERS_GROUP}}"]},"legal":{"legaltags":["{{LEGAL_TAG}}"],"otherRelevantDataCountries":["{{ISO_3166_ALPHA_2_CODE}}"]},"data":{"Name":"Normal","Code":"Normal","Description":"Dip-slip fault with hanging wall moving down relative to foot wall.","AttributionAuthority":"PPDM Association","Source":"Workbook curated by PPDM; commit SHA - No SHA (Workbook not committed).","CommitDate":"2023-10-24T21:55:03+00:00"}},{"id":"{{NAMESPACE}}:reference-data--SeismicFaultType:Oblique","kind":"osdu:wks:reference-data--SeismicFaultType:1.0.1","acl":{"owners":["{{DATA_OWNERS_GROUP}}"],"viewers":["{{DATA_VIEWERS_GROUP}}"]},"legal":{"legaltags":["{{LEGAL_TAG}}"],"otherRelevantDataCountries":["{{ISO_3166_ALPHA_2_CODE}}"]},"data":{"Name":"Oblique","Code":"Oblique","Description":"A fault with significant motion in strike and dip directions.","AttributionAuthority":"PPDM Association","Source":"Workbook curated by PPDM; commit SHA - No SHA (Workbook not committed).","CommitDate":"2023-10-24T21:55:03+00:00"}},{"id":"{{NAMESPACE}}:reference-data--SeismicFaultType:Reverse","kind":"osdu:wks:reference-data--SeismicFaultType:1.0.1","acl":{"owners":["{{DATA_OWNERS_GROUP}}"],"viewers":["{{DATA_VIEWERS_GROUP}}"]},"legal":{"legaltags":["{{LEGAL_TAG}}"],"otherRelevantDataCountries":["{{ISO_3166_ALPHA_2_CODE}}"]},"data":{"Name":"Reverse","Code":"Reverse","Description":"High angle dip-slip fault with hanging wall moving up relative to footwall.","AttributionAuthority":"PPDM Association","Source":"Workbook curated by PPDM; commit SHA - No SHA (Workbook not committed).","CommitDate":"2023-10-24T21:55:03+00:00"}},{"id":"{{NAMESPACE}}:reference-data--SeismicFaultType:StrikeSlip","kind":"osdu:wks:reference-data--SeismicFaultType:1.0.1","acl":{"owners":["{{DATA_OWNERS_GROUP}}"],"viewers":["{{DATA_VIEWERS_GROUP}}"]},"legal":{"legaltags":["{{LEGAL_TAG}}"],"otherRelevantDataCountries":["{{ISO_3166_ALPHA_2_CODE}}"]},"data":{"Name":"Strike-slip","Code":"StrikeSlip","Description":"Fault with lateral slip.","AttributionAuthority":"PPDM Association","Source":"Workbook curated by PPDM; commit SHA - No SHA (Workbook not committed).","CommitDate":"2023-10-24T21:55:03+00:00"}},{"id":"{{NAMESPACE}}:reference-data--SeismicFaultType:Thrust","kind":"osdu:wks:reference-data--SeismicFaultType:1.0.1","acl":{"owners":["{{DATA_OWNERS_GROUP}}"],"viewers":["{{DATA_VIEWERS_GROUP}}"]},"legal":{"legaltags":["{{LEGAL_TAG}}"],"otherRelevantDataCountries":["{{ISO_3166_ALPHA_2_CODE}}"]},"data":{"Name":"Thrust","Code":"Thrust","Description":"Low angle dip-slip fault with hanging wall moving up relative to footwall.","AttributionAuthority":"PPDM Association","Source":"Workbook curated by PPDM; commit SHA - No SHA (Workbook not committed).","CommitDate":"2023-10-24T21:55:03+00:00"}},{"id":"{{NAMESPACE}}:reference-data--SeismicFaultType:Strikeslip","kind":"osdu:wks:reference-data--SeismicFaultType:1.0.1","acl":{"owners":["{{DATA_OWNERS_GROUP}}"],"viewers":["{{DATA_VIEWERS_GROUP}}"]},"legal":{"legaltags":["{{LEGAL_TAG}}"],"otherRelevantDataCountries":["{{ISO_3166_ALPHA_2_CODE}}"]},"data":{"Name":"Strike-slip","Code":"Strikeslip","InactiveIndicator":true,"Description":"DEPRECATED: Please use Code=\"StrikeSlip\" with Name=\"Strike-slip\" instead. Fault with lateral slip.","AttributionAuthority":"PPDM Association","Source":"Workbook curated by PPDM; commit SHA - No SHA (Workbook not committed).","CommitDate":"2023-10-24T21:55:03+00:00"}}]}